README
setup.py
dfutils/__init__.py
dfutils/branch.py
dfutils/log.py
dfutils/sequencer.py
dfutils/sleep.py
dfutils.egg-info/PKG-INFO
dfutils.egg-info/SOURCES.txt
dfutils.egg-info/dependency_links.txt
dfutils.egg-info/top_level.txt