Metadata-Version: 1.0
Name: dfutils
Version: 0.0.2
Summary: Utilities to work with Twisted Deferreds.
Home-page: http://pypi.python.org/pypi/dfutils
Author: Claudiu Saftoiu
Author-email: csaftoiu@gmail.com
License: Public Domain
Keywords: twisted deferred utils
Platform: UNKNOWN
Classifier: Development Status :: 3 - Alpha
Classifier: Topic :: Utilities
Classifier: Framework :: Twisted
Classifier: License :: Public Domain
